llm_taxi/__init__.py
llm_taxi/cli.py
llm_taxi/conversation.py
llm_taxi/factory.py
llm_taxi/py.typed
llm_taxi/types.py
llm_taxi/utils.py
llm_taxi/clients/__init__.py
llm_taxi/clients/anthropic.py
llm_taxi/clients/base.py
llm_taxi/clients/bigmodel.py
llm_taxi/clients/dashscope.py
llm_taxi/clients/deepinfra.py
llm_taxi/clients/deepseek.py
llm_taxi/clients/google.py
llm_taxi/clients/groq.py
llm_taxi/clients/mistral.py
llm_taxi/clients/openai.py
llm_taxi/clients/openrouter.py
llm_taxi/clients/perplexity.py
llm_taxi/clients/together.py
llm_taxi/embeddings/__init__.py
llm_taxi/embeddings/base.py
llm_taxi/embeddings/google.py
llm_taxi/embeddings/mistral.py
llm_taxi/embeddings/openai.py
llm_taxi/embeddings/utils.py
llm_taxi/llms/__init__.py
llm_taxi/llms/anthropic.py
llm_taxi/llms/base.py
llm_taxi/llms/bigmodel.py
llm_taxi/llms/dashscope.py
llm_taxi/llms/deepinfra.py
llm_taxi/llms/deepseek.py
llm_taxi/llms/google.py
llm_taxi/llms/groq.py
llm_taxi/llms/mistral.py
llm_taxi/llms/openai.py
llm_taxi/llms/openrouter.py
llm_taxi/llms/perplexity.py
llm_taxi/llms/together.py
llm_taxi-0.7.0.dist-info/METADATA
llm_taxi-0.7.0.dist-info/WHEEL
llm_taxi-0.7.0.dist-info/entry_points.txt
llm_taxi-0.7.0.dist-info/RECORD
