Metadata-Version: 2.3
Name: llm-taxi
Version: 0.7.0
Summary: Call LLM as easily as calling a taxi.
Author-email: Yevgnen Koh <wherejoystarts@gmail.com>
Requires-Python: >=3.10
Requires-Dist: anthropic>=0.30.1
Requires-Dist: google-generativeai>=0.7.1
Requires-Dist: groq>=0.9.0
Requires-Dist: httpx[socks]>=0.27.0
Requires-Dist: mistralai>=1.0.2
Requires-Dist: openai>=1.35.10
Requires-Dist: pydantic>=2.7.1
Requires-Dist: together>=1.2.1
Requires-Dist: typing-extensions>=4.12.2
